<?xml version="1.0" encoding="UTF-8"?><record_update table="sp_row">
    <sp_row action="INSERT_OR_UPDATE">
        <class_name/>
        <order>1</order>
        <sp_column/>
        <sp_container display_value="KPI Dashboard - Container 2">059600b8db011010724a196c29961989</sp_container>
        <sys_class_name>sp_row</sys_class_name>
        <sys_created_by>Medni</sys_created_by>
        <sys_created_on>2020-05-25 08:36:54</sys_created_on>
        <sys_id>fda6c0b8db011010724a196c299619fa</sys_id>
        <sys_mod_count>0</sys_mod_count>
        <sys_name>1</sys_name>
        <sys_package display_value="KPID" source="x_353381_kpi">138ff324db011010724a196c2996191d</sys_package>
        <sys_policy/>
        <sys_scope display_value="KPID">138ff324db011010724a196c2996191d</sys_scope>
        <sys_update_name>sp_row_fda6c0b8db011010724a196c299619fa</sys_update_name>
        <sys_updated_by>Medni</sys_updated_by>
        <sys_updated_on>2020-05-25 08:36:54</sys_updated_on>
    </sp_row>
</record_update>
